[
  {
    "full_name": "discourse/discourse",
    "stargazers_count": 33328,
    "open_issues_count": 55,
    "forks_count": 7249
  },
  {
    "full_name": "ohmyzsh/ohmyzsh",
    "stargazers_count": 127921,
    "open_issues_count": 740,
    "forks_count": 22077
  },
  {
    "full_name": "scullyio/scully",
    "stargazers_count": 2156,
    "open_issues_count": 99,
    "forks_count": 220
  },
  {
    "full_name": "microsoft/TypeScript",
    "stargazers_count": 70977,
    "open_issues_count": 5271,
    "forks_count": 9340
  },
  {
    "full_name": "storybookjs/storybook",
    "stargazers_count": 61881,
    "open_issues_count": 1181,
    "forks_count": 6138
  },
  {
    "full_name": "Homebrew/brew",
    "stargazers_count": 27994,
    "open_issues_count": 50,
    "forks_count": 6235
  },
  {
    "full_name": "VSCodeVim/Vim",
    "stargazers_count": 8985,
    "open_issues_count": 1061,
    "forks_count": 938
  },
  {
    "full_name": "microsoft/vscode",
    "stargazers_count": 116074,
    "open_issues_count": 5334,
    "forks_count": 18920
  },
  {
    "full_name": "cli/cli",
    "stargazers_count": 23437,
    "open_issues_count": 345,
    "forks_count": 2344
  },
  {
    "full_name": "mdn/yari",
    "stargazers_count": 404,
    "open_issues_count": 241,
    "forks_count": 114
  }
]