[
  {
    "full_name": "discourse/discourse",
    "stargazers_count": 35809,
    "open_issues_count": 60,
    "forks_count": 7693
  },
  {
    "full_name": "ohmyzsh/ohmyzsh",
    "stargazers_count": 146104,
    "open_issues_count": 644,
    "forks_count": 24122
  },
  {
    "full_name": "scullyio/scully",
    "stargazers_count": 2404,
    "open_issues_count": 80,
    "forks_count": 246
  },
  {
    "full_name": "microsoft/TypeScript",
    "stargazers_count": 81245,
    "open_issues_count": 5492,
    "forks_count": 10607
  },
  {
    "full_name": "storybookjs/storybook",
    "stargazers_count": 71441,
    "open_issues_count": 1915,
    "forks_count": 7397
  },
  {
    "full_name": "Homebrew/brew",
    "stargazers_count": 32352,
    "open_issues_count": 43,
    "forks_count": 7695
  },
  {
    "full_name": "VSCodeVim/Vim",
    "stargazers_count": 10482,
    "open_issues_count": 1222,
    "forks_count": 1095
  },
  {
    "full_name": "microsoft/vscode",
    "stargazers_count": 132576,
    "open_issues_count": 6708,
    "forks_count": 22547
  },
  {
    "full_name": "cli/cli",
    "stargazers_count": 28814,
    "open_issues_count": 368,
    "forks_count": 3782
  },
  {
    "full_name": "mdn/yari",
    "stargazers_count": 814,
    "open_issues_count": 313,
    "forks_count": 318
  }
]